{
  "Apology Slime": {
    "MOVES": [],
    "NAME": "Przeprosinowy Szlam",
    "DIALOG": [
      ""
    ]
  },
  "CorruptHeart": {
    "MOVES": [
      ""
    ],
    "NAME": "Zepsute Serce",
    "DIALOG": [
      ""
    ]
  },
  "Nemesis": {
    "MOVES": [
      ""
    ],
    "NAME": "Nemezis",
    "DIALOG": [
      ""
    ]
  },
  "Chosen": {
    "MOVES": [
      ""
    ],
    "NAME": "Wybrana",
    "DIALOG": [
      "~Cierp...~"
    ]
  },
  "Byrd": {
    "MOVES": [
      ""
    ],
    "NAME": "Ptyk",
    "DIALOG": [
      "@KRA!@ NL @KRAAAA@",
      ""
    ]
  },
  "Snecko": {
    "MOVES": [
      "Spojrzenie Zamętu",
      "Trzaśnięcie Ogonem",
      "Ugryzienie"
    ],
    "NAME": "Jaszwąż",
    "DIALOG": [
      ""
    ]
  },
  "GremlinWizard": {
    "MOVES": [
      "Ładowanie",
      "Ładunek Ostateczny"
    ],
    "NAME": "Gremlin Mag",
    "DIALOG": [
      "",
      "Ładuję!",
      "~Już~ ~pr..~ ~..awie!!~",
      "@Ja...@ @muszę...@ NL @pomocy...!@",
      "~zbyt...~ NL ~niebezpiecznie...~ NL ~żegnaj...~"
    ]
  },
  "BanditChild": {
    "MOVES": [
      ""
    ],
    "NAME": "Spiczasty",
    "DIALOG": [
      "Niedźwieeeeeedź!!!!"
    ]
  },
  "Orb Walker": {
    "MOVES": [
      "Nabranie Siły"
    ],
    "NAME": "Piechur Sfery",
    "DIALOG": [
      "Inicjowanie NL tarcz."
    ]
  },
  "TheGuardian": {
    "MOVES": [
      "Tryb Defensywny",
      "Gwałtowne Grzmotnięcie",
      "Zwinięcie",
      "Podwójne Trzaśnięcie",
      "Trąba Powietrzna",
      "Ładowanie",
      "Ujście Pary"
    ],
    "NAME": "Obrońca",
    "DIALOG": [
      "#b~..CHŁO...~ NL #b~...DZENIE...~",
      "Bronienie...",
      "#r@ZNISZCZYĆ@ NL #r@ZNISZCZYĆ@ NL #r@ZNISZCZYĆ@",
      "#r@ZAGROŻENIE@ NL #r@ZAGROŻENIE@ NL #r@ZAGROŻENIE@"
    ]
  },
  "TheGuardianOrb": {
    "MOVES": [],
    "NAME": "",
    "DIALOG": []
  },
  "GremlinWarrior": {
    "MOVES": [
      "Drapnięcie"
    ],
    "NAME": "Szalony Gremlin",
    "DIALOG": [
      "",
      "@Muszę@ @iść@ NL @po@ @pomoc!@",
      "Juz mnie tu nie ma!"
    ]
  },
  "GremlinThief": {
    "MOVES": [
      ""
    ],
    "NAME": "Podstępny Gremlin",
    "DIALOG": [
      "",
      "@Chyba@ @pójdę@ NL @po@ @pomoc!@",
      "@Co@ @do!?@"
    ]
  },
  "Cultist": {
    "MOVES": [
      "",
      "",
      "Zaklęcie"
    ],
    "NAME": "Kultysta",
    "DIALOG": [
      "@MOJA@ @MOC@ @JEST@ NL @NIEDOŚCIGNIONA!@",
      "@NIE@ @NALEŻYSZ@ @DO@ NL @TEGO@ @MIEJSCA!@",
      "~Moja~ ~moc..~ NL ~została~ ~doścignięta...~"
    ]
  },
  "FlameBruiser": {
    "MOVES": [
      ""
    ],
    "NAME": "Czempion Ognia",
    "DIALOG": [
      ""
    ]
  },
  "GremlinLeader": {
    "MOVES": [
      "Do mnie!"
    ],
    "NAME": "Przywódca Gremlinów",
    "DIALOG": [
      "Nigdy się nie poddawaj!",
      "Jeszcze nie skończyliśmy!",
      "Na nich chłopcy!",
      "@Odwrót@ NL @Odwróóóót!@",
      "@Biegieeeem!@"
    ]
  },
  "Centurion": {
    "MOVES": [
      ""
    ],
    "NAME": "Centurion",
    "DIALOG": [
      ""
    ]
  },
  "GiantHead": {
    "MOVES": [
      ""
    ],
    "NAME": "Wielka Głowa",
    "DIALOG": [
      "~To~ ~już~ ~czas~",
      "~Do~ ~Widzenia~",
      "~Tik~ ~Tak~ NL ~Tik~ ~Tak~",
      "~Dlaczego~ ~ty~ ~tu~ NL ~dalej~ ~jesteś?~"
    ]
  },
  "BanditBear": {
    "MOVES": [
      ""
    ],
    "NAME": "Niedźwiedź",
    "DIALOG": [
      ""
    ]
  },
  "BanditLeader": {
    "MOVES": [
      ""
    ],
    "NAME": "Romeo",
    "DIALOG": [
      "Łap go Niedźwiedź!!",
      "Zapłacisz za to!!",
      "Nieeeeee, Niedźwiedź!"
    ]
  },
  "SpikeSlime_M": {
    "MOVES": [
      "Liźnięcie"
    ],
    "NAME": "Kolczasty Szlam (Ś)",
    "DIALOG": [
      ""
    ]
  },
  "SpikeSlime_S": {
    "MOVES": [],
    "NAME": "Kolczasty Szlam (M)",
    "DIALOG": [
      ""
    ]
  },
  "Mugger": {
    "MOVES": [
      "Wypad",
      "Wymuszenie"
    ],
    "NAME": "Złodziej",
    "DIALOG": [
      "Oddawaj!",
      "Znikam stąd!"
    ]
  },
  "TimeEater": {
    "MOVES": [
      ""
    ],
    "NAME": "Pożeracz Czasu",
    "DIALOG": [
      "~Ach...~ NL ~..towarzystwo...~",
      "~Głupi..~ NL @GŁUUUPI!@"
    ]
  },
  "TheCollector": {
    "MOVES": [
      ""
    ],
    "NAME": "Kolekcjoner",
    "DIALOG": [
      "@Jesteś@ @mój!@"
    ]
  },
  "TorchHead": {
    "MOVES": [
      ""
    ],
    "NAME": "Pochodniogłowy",
    "DIALOG": [
      ""
    ]
  },
  "AcidSlime_M": {
    "MOVES": [
      "Splucie Kwasem",
      "Liźnięcie"
    ],
    "NAME": "Kwasowy Szlam (Ś)",
    "DIALOG": [
      ""
    ]
  },
  "AcidSlime_S": {
    "MOVES": [],
    "NAME": "Kwasowy Szlam (M)",
    "DIALOG": [
      ""
    ]
  },
  "SnakePlant": {
    "MOVES": [
      "Osłabiające Zarodniki"
    ],
    "NAME": "Wężowa Roślina",
    "DIALOG": [
      ""
    ]
  },
  "Champ": {
    "MOVES": [
      "Pozycja Obronna",
      "Egzekucja",
      "Plaskacz"
    ],
    "NAME": "Mistrz",
    "DIALOG": [
      "Nazywasz to bronią?",
      "No dawaj!",
      "Pokaż co potrafisz! NL @HAHAHA!@",
      "Masz darmowy strzał! NL Żałosny słabeuszu!",
      "~Teraz~ ~to~ ~się~ ~doigrałeś...~",
      "@POKONANY??@ NL @NIEMOŻLIWE!!@",
      "~GIŃ~ ~.~ ~.~ ~.~",
      "Zmierz się z moim gniewem!"
    ]
  },
  "Exploder": {
    "MOVES": [
      ""
    ],
    "NAME": "Mina",
    "DIALOG": [
      ""
    ]
  },
  "FungiBeast": {
    "MOVES": [
      "Rośnięcie"
    ],
    "NAME": "Zgrzybiała Bestia",
    "DIALOG": [
      ""
    ]
  },
  "Spiker": {
    "MOVES": [
      ""
    ],
    "NAME": "Kolcarz",
    "DIALOG": [
      ""
    ]
  },
  "SlaverBoss": {
    "MOVES": [
      ""
    ],
    "NAME": "Nadzorca",
    "DIALOG": [
      ""
    ]
  },
  "Repulsor": {
    "MOVES": [
      ""
    ],
    "NAME": "Repulsator",
    "DIALOG": [
      ""
    ]
  },
  "Looter": {
    "MOVES": [
      "Pchnięcie",
      "Wymuszenie"
    ],
    "NAME": "Szabrownik",
    "DIALOG": [
      "Dawaj całe złoto!",
      "@NIEEEEeeee!@",
      "Gdzie jest moja bomba dymna... Może tutaj?...",
      "Dzięki za kasę, hehe"
    ]
  },
  "Sentry": {
    "MOVES": [
      "Zdezintegrowanie"
    ],
    "NAME": "Wartownik",
    "DIALOG": [
      ""
    ]
  },
  "FuzzyLouseDefensive": {
    "MOVES": [
      "Splunięcie Pajęczyną"
    ],
    "NAME": "Włochaty Wesz",
    "DIALOG": [
      ""
    ]
  },
  "FuzzyLouseNormal": {
    "MOVES": [
      "Rośnięcie"
    ],
    "NAME": "Włochaty Wesz",
    "DIALOG": [
      ""
    ]
  },
  "Puppeteer": {
    "MOVES": [
      ""
    ],
    "NAME": "Lalkarz",
    "DIALOG": [
      ""
    ]
  },
  "Shelled Parasite": {
    "MOVES": [
      ""
    ],
    "NAME": "Opancerzony pasożyt",
    "DIALOG": [
      ""
    ]
  },
  "BronzeOrb": {
    "MOVES": [
      ""
    ],
    "NAME": "Kula",
    "DIALOG": [
      ""
    ]
  },
  "Hexaghost": {
    "MOVES": [
      "Rozpalenie",
      "Przypalenie",
      "Inferno"
    ],
    "NAME": "Heksaduch",
    "DIALOG": []
  },
  "HexaghostBody": {
    "MOVES": [],
    "NAME": "",
    "DIALOG": []
  },
  "HexaghostOrb": {
    "MOVES": [],
    "NAME": "",
    "DIALOG": []
  },
  "SlaverRed": {
    "MOVES": [
      "Zadrapanie",
      "Zaplątanie"
    ],
    "NAME": "Łowca Niewolników",
    "DIALOG": [
      ""
    ]
  },
  "SlaverBlue": {
    "MOVES": [
      "Zadrapanie"
    ],
    "NAME": "Nadzorca Niewolników",
    "DIALOG": [
      ""
    ]
  },
  "SlimeBoss": {
    "MOVES": [
      "Trzaśnięcie",
      "Przygotowanie",
      "Podział",
      "Rozpylenie Szlamu"
    ],
    "NAME": "Szef Szlamu",
    "DIALOG": [
      "~Szlam...~ NL #r~MIAŻDŻYĆ!!!~",
      ""
    ]
  },
  "AcidSlime_L": {
    "MOVES": [
      "Splucie Kwasem",
      "Podział",
      "Polizanie"
    ],
    "NAME": "Kwasowy szlam (D)",
    "DIALOG": [
      ""
    ]
  },
  "GremlinTsundere": {
    "MOVES": [
      "Ochrona",
      "Walnięcie Tarczą"
    ],
    "NAME": "Gremlin Tarczownik",
    "DIALOG": [
      "",
      "~Do~ ~Widzenia...~",
      "To na nic..."
    ]
  },
  "Lagavulin": {
    "MOVES": [
      "Wyssanie duszy"
    ],
    "NAME": "Lagavulin",
    "DIALOG": [
      "",
      "... NL .....",
      "...? NL .....!?",
      "@!!!@ NL @!???@"
    ]
  },
  "JawWorm": {
    "MOVES": [
      "Ryk",
      "Wymłócenie"
    ],
    "NAME": "Szczękorobak",
    "DIALOG": [
      ""
    ]
  },
  "Donu": {
    "MOVES": [
      "Okrąg Mocy"
    ],
    "NAME": "Donu",
    "DIALOG": [
      ""
    ]
  },
  "Serpent": {
    "MOVES": [
      ""
    ],
    "NAME": "Wąż",
    "DIALOG": [
      ""
    ]
  },
  "BronzeAutomaton": {
    "MOVES": [
      "HIPER PROMIEŃ"
    ],
    "NAME": "Automaton z Brązu",
    "DIALOG": [
      ""
    ]
  },
  "Healer": {
    "MOVES": [
      ""
    ],
    "NAME": "Mistyk",
    "DIALOG": [
      ""
    ]
  },
  "GremlinFat": {
    "MOVES": [
      "Rozbicie"
    ],
    "NAME": "Gruby Gremlin",
    "DIALOG": [
      "",
      "",
      "@Och@ @nie,@ NL @och@ @nie,@ NL @OCH@ @NIE!@"
    ]
  },
  "Deca": {
    "MOVES": [
      ""
    ],
    "NAME": "Deca",
    "DIALOG": [
      ""
    ]
  },
  "BookOfStabbing": {
    "MOVES": [
      ""
    ],
    "NAME": "Księga Dźgnięć",
    "DIALOG": [
      ""
    ]
  },
  "AwakenedOne": {
    "MOVES": [
      "Duchowe Uderzenie",
      "Mroczne Echo",
      "Oczyszczenie",
      "Muł"
    ],
    "NAME": "Przebudzony",
    "DIALOG": [
      "~Grr~ ~.~ ~.~ ~.~",
      "~Nie~ ~.~ ~.~ ~.~ ~nie~ ~.~ ~.~ NL ~.~ ~.~ ~nie~ ~.~ ~.~ ~.~"
    ]
  },
  "SpikeSlime_L": {
    "MOVES": [
      "Liźnięcie",
      "Podział"
    ],
    "NAME": "Kolczasty Szlam (D)",
    "DIALOG": [
      ""
    ]
  },
  "FireOrb": {
    "MOVES": [
      ""
    ],
    "NAME": "Ognista Kula",
    "DIALOG": [
      ""
    ]
  },
  "SphericGuardian": {
    "MOVES": [
      ""
    ],
    "NAME": "Okrągły Obrońca",
    "DIALOG": [
      "~Obcy~ NL ~Wykryty~"
    ]
  },
  "Darkling": {
    "MOVES": [
      "Chrup! Chrup!"
    ],
    "NAME": "Zrodzony z mroku",
    "DIALOG": [
      "Odrastanie..."
    ]
  },
  "Maw": {
    "MOVES": [
      ""
    ],
    "NAME": "Trawieniec",
    "DIALOG": [
      "@RRrrohrrRGHhh!!@"
    ]
  },
  "GremlinNob": {
    "MOVES": [
      "Zmiażdzenie czaszki",
      "Szarża Rogami"
    ],
    "NAME": "Gremlin Pałownik",
    "DIALOG": [
      "@RRrroohrrRGHHhhh!!@"
    ]
  }
}